{
    "coord": {
        "lon": 6.1423,
        "lat": 46.2047
    },
    "weather": [
        {
            "id": 802,
            "main": "Clouds",
            "description": "scattered clouds",
            "icon": "03d"
        }
    ],
    "base": "stations",
    "main": {
        "temp": 13.22,
        "feels_like": 11.51,
        "temp_min": 11.84,
        "temp_max": 14.49,
        "pressure": 999,
        "humidity": 35
    },
    "visibility": 10000,
    "wind": {
        "speed": 7.2,
        "deg": 200
    },
    "clouds": {
        "all": 40
    },
    "dt": 1711632322,
    "sys": {
        "type": 1,
        "id": 6928,
        "country": "CH",
        "sunrise": 1711603338,
        "sunset": 1711648696
    },
    "timezone": 3600,
    "id": 7285902,
    "name": "Geneva",
    "cod": 200
}